ionoscloud_dbaas_postgres/__init__.py
ionoscloud_dbaas_postgres/api_client.py
ionoscloud_dbaas_postgres/api_response.py
ionoscloud_dbaas_postgres/configuration.py
ionoscloud_dbaas_postgres/exceptions.py
ionoscloud_dbaas_postgres/rest.py
ionoscloud_dbaas_postgres/test-driver.py
ionoscloud_dbaas_postgres/api/__init__.py
ionoscloud_dbaas_postgres/api/backups_api.py
ionoscloud_dbaas_postgres/api/clusters_api.py
ionoscloud_dbaas_postgres/api/databases_api.py
ionoscloud_dbaas_postgres/api/logs_api.py
ionoscloud_dbaas_postgres/api/metadata_api.py
ionoscloud_dbaas_postgres/api/restores_api.py
ionoscloud_dbaas_postgres/api/users_api.py
ionoscloud_dbaas_postgres/models/__init__.py
ionoscloud_dbaas_postgres/models/api_version.py
ionoscloud_dbaas_postgres/models/backup_location.py
ionoscloud_dbaas_postgres/models/backup_metadata.py
ionoscloud_dbaas_postgres/models/backup_response.py
ionoscloud_dbaas_postgres/models/cluster_backup.py
ionoscloud_dbaas_postgres/models/cluster_backup_list.py
ionoscloud_dbaas_postgres/models/cluster_backup_list_all_of.py
ionoscloud_dbaas_postgres/models/cluster_list.py
ionoscloud_dbaas_postgres/models/cluster_list_all_of.py
ionoscloud_dbaas_postgres/models/cluster_logs.py
ionoscloud_dbaas_postgres/models/cluster_logs_instances.py
ionoscloud_dbaas_postgres/models/cluster_logs_instances_messages.py
ionoscloud_dbaas_postgres/models/cluster_logs_messages.py
ionoscloud_dbaas_postgres/models/cluster_metadata.py
ionoscloud_dbaas_postgres/models/cluster_properties.py
ionoscloud_dbaas_postgres/models/cluster_response.py
ionoscloud_dbaas_postgres/models/connection.py
ionoscloud_dbaas_postgres/models/create_cluster_properties.py
ionoscloud_dbaas_postgres/models/create_cluster_request.py
ionoscloud_dbaas_postgres/models/create_restore_request.py
ionoscloud_dbaas_postgres/models/database.py
ionoscloud_dbaas_postgres/models/database_items.py
ionoscloud_dbaas_postgres/models/database_list.py
ionoscloud_dbaas_postgres/models/database_properties.py
ionoscloud_dbaas_postgres-1.2.0.dist-info/LICENSE
ionoscloud_dbaas_postgres-1.2.0.dist-info/METADATA
ionoscloud_dbaas_postgres-1.2.0.dist-info/WHEEL
ionoscloud_dbaas_postgres-1.2.0.dist-info/top_level.txt
ionoscloud_dbaas_postgres-1.2.0.dist-info/RECORD
