Metadata-Version: 2.1
Name: ionoscloud-dbaas-postgres
Version: 1.2.0
Summary: Python SDK for the Ionos DBaaS Postgres API
Home-page: https://github.com/ionos-cloud/sdk-python-dbaas-postgres
Author: Ionos Cloud
Author-email: sdk@cloud.ionos.com
Keywords: OpenAPI,OpenAPI-Generator,IONOS DBaaS PostgreSQL REST API
Classifier: Natural Language :: English
Classifier: Environment :: Web Environment
Classifier: Intended Audience :: Developers
Classifier: License :: OSI Approved :: Apache Software License
Classifier: Operating System :: POSIX
Classifier: Programming Language :: Python
Classifier: Programming Language :: Python :: 3
Classifier: Topic :: Software Development :: Libraries :: Python Modules
Classifier: Topic :: Software Development :: Libraries :: Application Frameworks
Classifier: Topic :: Internet :: WWW/HTTP
License-File: LICENSE
Requires-Dist: urllib3 (>=1.15)
Requires-Dist: six (>=1.10)
Requires-Dist: certifi
Requires-Dist: python-dateutil
Requires-Dist: asn1crypto
